LICENSE
MANIFEST.in
README.md
pyproject.toml
setup.py
src/clone_competition_simulation/__init__.py
src/clone_competition_simulation/utils.py
src/clone_competition_simulation.egg-info/PKG-INFO
src/clone_competition_simulation.egg-info/SOURCES.txt
src/clone_competition_simulation.egg-info/dependency_links.txt
src/clone_competition_simulation.egg-info/requires.txt
src/clone_competition_simulation.egg-info/top_level.txt
src/clone_competition_simulation/analysis/__init__.py
src/clone_competition_simulation/analysis/analysis.py
src/clone_competition_simulation/fitness/__init__.py
src/clone_competition_simulation/fitness/fitness_classes.py
src/clone_competition_simulation/parameters/__init__.py
src/clone_competition_simulation/parameters/algorithm_validation.py
src/clone_competition_simulation/parameters/differentiated_cells_validation.py
src/clone_competition_simulation/parameters/fitness_validation.py
src/clone_competition_simulation/parameters/label_validation.py
src/clone_competition_simulation/parameters/parameter_validation.py
src/clone_competition_simulation/parameters/plotting_validation.py
src/clone_competition_simulation/parameters/population_validation.py
src/clone_competition_simulation/parameters/times_validation.py
src/clone_competition_simulation/parameters/treatment_validation.py
src/clone_competition_simulation/parameters/validation_utils.py
src/clone_competition_simulation/plotting/__init__.py
src/clone_competition_simulation/plotting/animator.py
src/clone_competition_simulation/plotting/colourscales.py
src/clone_competition_simulation/simulation_algorithms/__init__.py
src/clone_competition_simulation/simulation_algorithms/branching_process.py
src/clone_competition_simulation/simulation_algorithms/diff_cell_functions.c
src/clone_competition_simulation/simulation_algorithms/diff_cell_functions.pyx
src/clone_competition_simulation/simulation_algorithms/general_2D_class.py
src/clone_competition_simulation/simulation_algorithms/general_differentiated_cell_class.py
src/clone_competition_simulation/simulation_algorithms/general_sim_class.py
src/clone_competition_simulation/simulation_algorithms/moran.py
src/clone_competition_simulation/simulation_algorithms/moran2D.py
