Metadata-Version: 2.4
Name: clone-competition-simulation
Version: 0.1.4
Summary: Python simulations of clone competition during ongoing mutagenesis.
Author-email: Michael Hall <mh28@sanger.ac.uk>
Requires-Python: >=3.11
License-File: LICENSE
Requires-Dist: cython>=3.2.1
Requires-Dist: cythongsl>=0.2.2
Requires-Dist: dill>=0.4.0
Requires-Dist: loguru>=0.7.3
Requires-Dist: matplotlib>=3.10.7
Requires-Dist: numpy>=2.2.6
Requires-Dist: pandas>=2.3.3
Requires-Dist: pydantic>=2.12.5
Requires-Dist: pydantic-settings>=2.12.0
Requires-Dist: pyyaml>=6.0.3
Requires-Dist: scipy>=1.15.3
Requires-Dist: seaborn>=0.13.2
Requires-Dist: setuptools>=80.9.0
Requires-Dist: treelib>=1.8.0
Dynamic: license-file
